threedi_edits/__init__.py
threedi_edits/globals.py
threedi_edits/examples/__init__.py
threedi_edits/examples/dem_sampling.py
threedi_edits/examples/dem_sampling_linestrings.py
threedi_edits/examples/extract_raster_data_using_geometries.py
threedi_edits/examples/interpolate_threedi_results.py
threedi_edits/examples/merge_vector_files.py
threedi_edits/examples/merging_linestrings_based_on_heights.py
threedi_edits/examples/profielen_overijssels_kanaal_to_threedi.py
threedi_edits/examples/raster_alignment.py
threedi_edits/examples/sideview.py
threedi_edits/examples/threedi_model_edits.py
threedi_edits/examples/threedi_raster_extraction.py
threedi_edits/examples/vonoroi_polygons_from_linestrings.py
threedi_edits/gis/__init__.py
threedi_edits/gis/feature.py
threedi_edits/gis/fields.py
threedi_edits/gis/geometry.py
threedi_edits/gis/geotransform.py
threedi_edits/gis/linestring.py
threedi_edits/gis/point.py
threedi_edits/gis/polygon.py
threedi_edits/gis/raster.py
threedi_edits/gis/rastergroup.py
threedi_edits/gis/spatial_reference.py
threedi_edits/gis/utils.py
threedi_edits/gis/vector.py
threedi_edits/gis/vectorbase.py
threedi_edits/gis/vectorgroup.py
threedi_edits/tests/__init__.py
threedi_edits/tests/benchmark.json
threedi_edits/tests/test_gis_feature.py
threedi_edits/tests/test_gis_geometry.py
threedi_edits/tests/test_gis_linestring.py
threedi_edits/tests/test_gis_polygon.py
threedi_edits/tests/test_gis_raster.py
threedi_edits/tests/test_gis_rastergroup.py
threedi_edits/tests/test_gis_vector.py
threedi_edits/tests/test_gis_vectorbase.py
threedi_edits/tests/test_threedi_edits.py
threedi_edits/tests/test_threedi_rastergroup.py
threedi_edits/tests/data/gis_feature.gpkg
threedi_edits/tests/data/gis_geometry.gpkg
threedi_edits/tests/data/gis_linestring.gpkg
threedi_edits/tests/data/gis_raster.gpkg
threedi_edits/tests/data/gis_raster_group.gpkg
threedi_edits/tests/data/gis_vector.gpkg
threedi_edits/tests/data/threedi_edits.gpkg
threedi_edits-1.2.2.dist-info/LICENSE
threedi_edits-1.2.2.dist-info/METADATA
threedi_edits-1.2.2.dist-info/WHEEL
threedi_edits-1.2.2.dist-info/entry_points.txt
threedi_edits-1.2.2.dist-info/top_level.txt
threedi_edits-1.2.2.dist-info/RECORD
