Metadata-Version: 2.1
Name: threedi-edits
Version: 1.2.2
Summary: An experimental pythonic 3Di schematisation api. Using this api, we can access, alter en write a 3Di database within python. Within the package gis tools are provided as well. 
Home-page: https://github.com/threedi-edits
Author: Chris Kerklaan
Author-email: chris-kerklaan@live.nl
License: LGPL
Keywords: 3Di,GDAL,api
Classifier: Programming Language :: Python
Classifier: Framework :: Django
Requires-Python: <3.11
License-File: LICENSE
Requires-Dist: scipy
Requires-Dist: cached-property
Requires-Dist: shapely (==2.0a1)
Requires-Dist: threedigrid-builder
Requires-Dist: threedi-modelchecker
Provides-Extra: test
Requires-Dist: pytest ; extra == 'test'
Requires-Dist: mock ; extra == 'test'
Requires-Dist: pytest-cov ; extra == 'test'
Requires-Dist: pytest-flakes ; extra == 'test'
Requires-Dist: pytest-black ; extra == 'test'
Requires-Dist: pytest-benchmark ; extra == 'test'
